telegram_notifier/__init__.py
telegram_notifier/exceptions.py
telegram_notifier/logger.py
telegram_notifier/notifier_main.py
telegram_notifier/utils.py
telegram_notifier_ekt-1.0.4.dist-info/METADATA
telegram_notifier_ekt-1.0.4.dist-info/WHEEL
telegram_notifier_ekt-1.0.4.dist-info/top_level.txt
telegram_notifier_ekt-1.0.4.dist-info/RECORD
