Metadata-Version: 2.4
Name: telegram-notifier-ekt
Version: 1.0.4
Summary: Paquete reutilizable para enviar notificaciones por Telegram
Author: roan
Keywords: telegram,notification,bot,alerts
Classifier: Development Status :: 4 - Beta
Classifier: Intended Audience :: Developers
Classifier: License :: OSI Approved :: MIT License
Classifier: Operating System :: OS Independent
Classifier: Programming Language :: Python :: 3
Classifier: Programming Language :: Python :: 3.7
Classifier: Programming Language :: Python :: 3.8
Classifier: Programming Language :: Python :: 3.9
Classifier: Programming Language :: Python :: 3.10
Classifier: Programming Language :: Python :: 3.11
Requires-Python: >=3.7
Requires-Dist: anyio==4.12.0
Requires-Dist: certifi==2025.11.12
Requires-Dist: h11==0.16.0
Requires-Dist: httpcore==1.0.9
Requires-Dist: httpx==0.28.1
Requires-Dist: idna==3.11
Requires-Dist: python-telegram-bot==22.5
Requires-Dist: requests>=2.25.0
Requires-Dist: python-dotenv>=0.19.0
Dynamic: author
Dynamic: classifier
Dynamic: description
Dynamic: description-content-type
Dynamic: keywords
Dynamic: requires-dist
Dynamic: requires-python
Dynamic: summary
